mcp_server/__init__.py
mcp_server/analyzers/__init__.py
mcp_server/analyzers/base.py
mcp_server/analyzers/business_analyzer.py
mcp_server/analyzers/factory.py
mcp_server/analyzers/fastapi.py
mcp_server/analyzers/openapi.py
mcp_server/analyzers/spring_boot.py
mcp_server/clients/__init__.py
mcp_server/clients/bitbucket.py
mcp_server/clients/git.py
mcp_server/generators/__init__.py
mcp_server/generators/business_report.py
mcp_server/generators/postman.py
mcp_server/main.py
mcp_server/models/__init__.py
mcp_server/models/api.py
mcp_server/models/business.py
mcp_server/models/postman.py
mcp_server/utils/__init__.py
mcp_server/utils/errors.py
mcp_server/utils/validators.py
postman_collection_generator_mcp-0.2.12.dist-info/LICENSE
postman_collection_generator_mcp-0.2.12.dist-info/METADATA
postman_collection_generator_mcp-0.2.12.dist-info/WHEEL
postman_collection_generator_mcp-0.2.12.dist-info/entry_points.txt
postman_collection_generator_mcp-0.2.12.dist-info/RECORD
