Metadata-Version: 2.3
Name: postman-collection-generator-mcp
Version: 0.2.12
Summary: MCP server for generating Postman collections from API codebases
License: MIT
Keywords: mcp,postman,api,collection,generator
Author: Your Name
Author-email: you@example.com
Requires-Python: >=3.12,<4.0
Classifier: Development Status :: 4 - Beta
Classifier: Intended Audience :: Developers
Classifier: License :: OSI Approved :: MIT License
Classifier: Programming Language :: Python :: 3
Classifier: Programming Language :: Python :: 3.12
Classifier: Programming Language :: Python :: 3.13
Requires-Dist: fastmcp (>=2.10.0,<3.0.0)
Requires-Dist: gitpython (>=3.1.40,<4.0.0)
Requires-Dist: pydantic (>=2.0.0,<3.0.0)
Requires-Dist: pyyaml (>=6.0.0,<7.0.0)
Requires-Dist: requests (>=2.31.0,<3.0.0)
Requires-Dist: rich (>=13.0.0,<14.0.0)
Project-URL: Homepage, https://github.com/yourusername/postman-collection-generator-mcp
Project-URL: Repository, https://github.com/yourusername/postman-collection-generator-mcp
